urlprettify/__init__.py
urlprettify/__main__.py
urlprettify/urlprettify.py
urlprettify-0.0.8.dist-info/LICENSE
urlprettify-0.0.8.dist-info/METADATA
urlprettify-0.0.8.dist-info/WHEEL
urlprettify-0.0.8.dist-info/top_level.txt
urlprettify-0.0.8.dist-info/RECORD
