Metadata-Version: 2.1
Name: urlprettify
Version: 0.0.8
Summary: Prettify URL to use only FQDN or IP-address
Author-email: Igor Potapov <garrych@ya.ru>
License: Copyright (c) 2018 The Python Packaging Authority
Keywords: url,pretty
Classifier: License :: OSI Approved :: MIT License
Classifier: Operating System :: OS Independent
Classifier: Programming Language :: Python :: 3
Requires-Python: >=3.9
License-File: LICENSE
